atp_tennis_scraper/__init__.py
atp_tennis_scraper/main.py
atp_tennis_scraper-0.1.1.dist-info/LICENSE
atp_tennis_scraper-0.1.1.dist-info/METADATA
atp_tennis_scraper-0.1.1.dist-info/WHEEL
atp_tennis_scraper-0.1.1.dist-info/top_level.txt
atp_tennis_scraper-0.1.1.dist-info/RECORD
