Metadata-Version: 2.2
Name: atp_tennis_scraper
Version: 0.1.1
Summary: A Python package for scraping ATP tennis rankings.
Home-page: https://github.com/Semne77/atp_tennis_scraper
Author: Semyon Tsyrenov
Author-email: tsyrenovsemyon@gmail.com
Classifier: Programming Language :: Python :: 3
Classifier: License :: OSI Approved :: MIT License
Classifier: Operating System :: OS Independent
Requires-Python: >=3.7
License-File: LICENSE
Requires-Dist: requests
Requires-Dist: beautifulsoup4
Dynamic: author
Dynamic: author-email
Dynamic: classifier
Dynamic: description
Dynamic: description-content-type
Dynamic: home-page
Dynamic: requires-dist
Dynamic: requires-python
Dynamic: summary
